{
  "gitSyncId": "681837a3d01125478949ff12_d7f97f8b-b6b4-4990-b991-c6d95bfe6a78",
  "id": "login_Query2",
  "pluginId": "mysql-plugin",
  "pluginType": "DB",
  "unpublishedAction": {
    "actionConfiguration": {
      "body": "SELECT *\nFROM `kaddname`\nWHERE `code` = '{{Input1.text}}'\n  AND `password` = '{{Input2.text}}'\nLIMIT 1;",
      "encodeParamsToggle": true,
      "paginationType": "NONE",
      "pluginSpecifiedTemplates": [
        {
          "value": true
        }
      ],
      "timeoutInMillisecond": 10000
    },
    "confirmBeforeExecute": false,
    "datasource": {
      "id": "restoredb.dynns.com3306",
      "isAutoGenerated": false,
      "name": "restoredb.dynns.com3306",
      "pluginId": "mysql-plugin"
    },
    "dynamicBindingPathList": [
      {
        "key": "body"
      }
    ],
    "executeOnLoad": false,
    "name": "Query2",
    "pageId": "login",
    "userSetOnLoad": false
  }
}