{
  "animateLoading": true,
  "borderRadius": "{{appsmith.theme.borderRadius.appBorderRadius}}",
  "bottomRow": 5,
  "dynamicBindingPathList": [
    {
      "key": "truncateButtonColor"
    },
    {
      "key": "fontFamily"
    },
    {
      "key": "borderRadius"
    }
  ],
  "dynamicHeight": "AUTO_HEIGHT",
  "dynamicTriggerPathList": [],
  "fontFamily": "{{appsmith.theme.fontFamily.appFont}}",
  "fontSize": "1.875rem",
  "fontStyle": "BOLD",
  "isLoading": false,
  "isVisible": true,
  "key": "hmeaydjrh9",
  "leftColumn": 12,
  "maxDynamicHeight": 9000,
  "minDynamicHeight": 4,
  "minWidth": 450,
  "mobileBottomRow": 13,
  "mobileLeftColumn": 51,
  "mobileRightColumn": 62,
  "mobileTopRow": 9,
  "needsErrorInfo": false,
  "originalBottomRow": 5,
  "originalTopRow": 0,
  "overflow": "NONE",
  "parentColumnSpace": 17.9375,
  "parentId": "rfixhqz3tc",
  "parentRowSpace": 10,
  "renderMode": "CANVAS",
  "responsiveBehavior": "fill",
  "rightColumn": 46,
  "shouldTruncate": false,
  "text": "เช็คข้อมูลเครื่องจักร",
  "textAlign": "LEFT",
  "textColor": "#231F20",
  "topRow": 0,
  "truncateButtonColor": "{{appsmith.theme.colors.primaryColor}}",
  "type": "TEXT_WIDGET",
  "version": 1,
  "widgetId": "ano169c2bc",
  "widgetName": "Text2"
}