{
  "gitSyncId": "681837a3d01125478949ff12_6780dae7-5e7a-44f0-81dc-81a9a5d481e1",
  "unpublishedPage": {
    "isHidden": true,
    "layouts": [
      {
        "dsl": {
          "backgroundColor": "none",
          "bottomRow": 950,
          "canExtend": true,
          "containerStyle": "none",
          "detachFromLayout": true,
          "dynamicBindingPathList": [],
          "leftColumn": 0,
          "minHeight": 930,
          "parentColumnSpace": 1,
          "parentRowSpace": 1,
          "rightColumn": 1224,
          "snapColumns": 64,
          "snapRows": 91,
          "topRow": 0,
          "type": "CANVAS_WIDGET",
          "version": 94,
          "widgetId": "0",
          "widgetName": "MainContainer"
        }
      }
    ],
    "name": "เทสการอัพข้อมูลลงตาราง",
    "slug": ""
  }
}